aigc_evals/__init__.py
aigc_evals/api.py
aigc_evals/base.py
aigc_evals/data.py
aigc_evals/data_test.py
aigc_evals/eval.py
aigc_evals/formatting.py
aigc_evals/metrics.py
aigc_evals/record.py
aigc_evals/record_test.py
aigc_evals/registry.py
aigc_evals/registry_test.py
aigc_evals/__pycache__/__init__.cpython-38.pyc
aigc_evals/__pycache__/api.cpython-38.pyc
aigc_evals/__pycache__/base.cpython-38.pyc
aigc_evals/__pycache__/data.cpython-38.pyc
aigc_evals/__pycache__/eval.cpython-38.pyc
aigc_evals/__pycache__/record.cpython-38.pyc
aigc_evals/__pycache__/registry.cpython-38.pyc
aigc_evals/cli/__init__.py
aigc_evals/cli/exec_aigc_evals.py
aigc_evals/cli/__pycache__/__init__.cpython-38.pyc
aigc_evals/completion_fns/__init__.py
aigc_evals/completion_fns/cot.py
aigc_evals/completion_fns/langchain_llm.py
aigc_evals/completion_fns/langchain_math.py
aigc_evals/completion_fns/openai.py
aigc_evals/completion_fns/retrieval.py
aigc_evals/completion_fns/__pycache__/__init__.cpython-38.pyc
aigc_evals/completion_fns/__pycache__/openai.cpython-38.pyc
aigc_evals/elsuite/__init__.py
aigc_evals/elsuite/lambada.py
aigc_evals/elsuite/multiple_choice.py
aigc_evals/elsuite/translate.py
aigc_evals/elsuite/utils.py
aigc_evals/elsuite/utils_test.py
aigc_evals/elsuite/__pycache__/__init__.cpython-38.pyc
aigc_evals/elsuite/basic/__init__.py
aigc_evals/elsuite/basic/fuzzy_match.py
aigc_evals/elsuite/basic/fuzzy_match_test.py
aigc_evals/elsuite/basic/includes.py
aigc_evals/elsuite/basic/includes_test.py
aigc_evals/elsuite/basic/json_validator.py
aigc_evals/elsuite/basic/json_validator_test.py
aigc_evals/elsuite/basic/match.py
aigc_evals/elsuite/basic/match_test.py
aigc_evals/elsuite/modelgraded/__init__.py
aigc_evals/elsuite/modelgraded/base.py
aigc_evals/elsuite/modelgraded/classify.py
aigc_evals/elsuite/modelgraded/classify_utils.py
aigc_evals/elsuite/modelgraded/__pycache__/__init__.cpython-38.pyc
aigc_evals/elsuite/modelgraded/__pycache__/base.cpython-38.pyc
aigc_evals/elsuite/test/__init__.py
aigc_evals-0.0.3.dist-info/LICENSE
aigc_evals-0.0.3.dist-info/METADATA
aigc_evals-0.0.3.dist-info/WHEEL
aigc_evals-0.0.3.dist-info/entry_points.txt
aigc_evals-0.0.3.dist-info/top_level.txt
aigc_evals-0.0.3.dist-info/RECORD
